Atrajit/__init__.py
Atrajit/Cryptography/__init__.py
Atrajit/Cryptography/decrypt.py
Atrajit/Cryptography/encrypt.py
Atrajit/Maths/__init__.py
Atrajit/Maths/linear_alg.py
Atrajit/Maths/numbertheory.py
Atrajit/Maths/switch.py
Atrajit/Telebot/TELEBOT_API.py
Atrajit/Telebot/__init__.py
Atrajit-3.0.dist-info/METADATA
Atrajit-3.0.dist-info/WHEEL
Atrajit-3.0.dist-info/top_level.txt
Atrajit-3.0.dist-info/RECORD
