Metadata-Version: 2.1
Name: Atrajit
Version: 3.0
Summary: A Python package that includes Cryptography, Maths, and Telebot modules
Home-page: https://github.com/atrajit-sarkar/Atr
Author: atrajit-sarkar
Author-email: atrajit.sarkar@gmail.com
Classifier: Programming Language :: Python :: 3
Classifier: License :: OSI Approved :: MIT License
Classifier: Operating System :: OS Independent
Requires-Python: >=3.6
Requires-Dist: cryptography>=43.0.0
